{
  "items": {
    "items": [
      {
        "svg": "<svg xmlns=\"http://www.w3.org/2000/svg\"\n                     xmlns:xlink=\"http://www.w3.org/1999/xlink\"\n                     width=\"43.5px\" height=\"51.5px\">\n                    <path fill-rule=\"evenodd\" stroke=\"rgb(65, 54, 89)\" stroke-width=\"1px\" stroke-linecap=\"butt\" stroke-linejoin=\"miter\" fill=\"none\"\n                          d=\"M28.566,50.499 L3.167,50.499 C1.787,50.499 0.668,49.380 0.668,47.999 L0.668,3.001 C0.668,1.620 1.787,0.501 3.167,0.501 L39.833,0.501 C41.213,0.501 42.332,1.620 42.332,3.001 L42.332,36.732 L28.566,50.499 Z\" />\n                    <path fill-rule=\"evenodd\" fill=\"rgb(217, 215, 222)\"\n                          d=\"M42.332,38.000 L29.833,50.499 L29.000,50.499 L29.000,37.166 L42.332,37.166 L42.332,38.000 Z\" />\n                    <path fill-rule=\"evenodd\" fill=\"rgb(65, 54, 89)\"\n                          d=\"M13.316,28.828 L14.007,29.514 L10.343,33.146 L9.652,33.831 L8.960,33.146 L7.335,31.535 L8.027,30.850 L9.652,32.461 L13.316,28.828 Z\" />\n                    <path fill-rule=\"evenodd\" opacity=\"0.251\" fill=\"rgb(65, 54, 89)\"\n                          d=\"M17.334,31.333 L33.999,31.333 L33.999,32.166 L17.334,32.166 L17.334,31.333 Z\" />\n                    <path fill-rule=\"evenodd\" fill=\"rgb(65, 54, 89)\"\n                          d=\"M13.316,18.829 L14.007,19.514 L10.343,23.146 L9.652,23.832 L8.960,23.146 L7.335,21.536 L8.027,20.850 L9.652,22.461 L13.316,18.829 Z\" />\n                    <path fill-rule=\"evenodd\" opacity=\"0.251\" fill=\"rgb(65, 54, 89)\"\n                          d=\"M17.334,21.334 L33.999,21.334 L33.999,22.167 L17.334,22.167 L17.334,21.334 Z\" />\n                    <path fill-rule=\"evenodd\" fill=\"rgb(65, 54, 89)\"\n                          d=\"M13.316,8.829 L14.007,9.514 L10.343,13.147 L9.652,13.832 L8.960,13.147 L7.335,11.536 L8.027,10.851 L9.652,12.461 L13.316,8.829 Z\" />\n                    <path fill-rule=\"evenodd\" opacity=\"0.251\" fill=\"rgb(65, 54, 89)\"\n                          d=\"M17.334,11.334 L33.999,11.334 L33.999,12.167 L17.334,12.167 L17.334,11.334 Z\" />\n                </svg>",
        "svgTrusted": {},
        "css": "",
        "text": "Provider Registration Form",
        "key": "providerRegister",
        "tabs": "",
        "fields": "-hideFields,-contactRecipientEmailAddress,+formHeading,+formSecondaryHeading,+formIntroduction,+formButtonText,+formSubmissionMessage,-formSubscriberListID,-umbracoForm,-loginSuccessPage,-loginFormPage,-resetPasswordRequestPage,-resetPasswordPage,-resetPasswordEmail,+adminApprovalRequired,+emailConfirmationRequired,+memberConfirmationEmail,+setEmailAddressAsUsername"
      },
      {
        "svg": "<svg xmlns=\"http://www.w3.org/2000/svg\"\n                     xmlns:xlink=\"http://www.w3.org/1999/xlink\"\n                     width=\"43.5px\" height=\"51.5px\">\n                    <path fill-rule=\"evenodd\" stroke=\"rgb(65, 54, 89)\" stroke-width=\"1px\" stroke-linecap=\"butt\" stroke-linejoin=\"miter\" fill=\"none\"\n                          d=\"M28.566,50.499 L3.167,50.499 C1.787,50.499 0.668,49.380 0.668,47.999 L0.668,3.001 C0.668,1.620 1.787,0.501 3.167,0.501 L39.833,0.501 C41.213,0.501 42.332,1.620 42.332,3.001 L42.332,36.732 L28.566,50.499 Z\" />\n                    <path fill-rule=\"evenodd\" fill=\"rgb(217, 215, 222)\"\n                          d=\"M42.332,38.000 L29.833,50.499 L29.000,50.499 L29.000,37.166 L42.332,37.166 L42.332,38.000 Z\" />\n                    <path fill-rule=\"evenodd\" fill=\"rgb(65, 54, 89)\"\n                          d=\"M13.316,28.828 L14.007,29.514 L10.343,33.146 L9.652,33.831 L8.960,33.146 L7.335,31.535 L8.027,30.850 L9.652,32.461 L13.316,28.828 Z\" />\n                    <path fill-rule=\"evenodd\" opacity=\"0.251\" fill=\"rgb(65, 54, 89)\"\n                          d=\"M17.334,31.333 L33.999,31.333 L33.999,32.166 L17.334,32.166 L17.334,31.333 Z\" />\n                    <path fill-rule=\"evenodd\" fill=\"rgb(65, 54, 89)\"\n                          d=\"M13.316,18.829 L14.007,19.514 L10.343,23.146 L9.652,23.832 L8.960,23.146 L7.335,21.536 L8.027,20.850 L9.652,22.461 L13.316,18.829 Z\" />\n                    <path fill-rule=\"evenodd\" opacity=\"0.251\" fill=\"rgb(65, 54, 89)\"\n                          d=\"M17.334,21.334 L33.999,21.334 L33.999,22.167 L17.334,22.167 L17.334,21.334 Z\" />\n                    <path fill-rule=\"evenodd\" fill=\"rgb(65, 54, 89)\"\n                          d=\"M13.316,8.829 L14.007,9.514 L10.343,13.147 L9.652,13.832 L8.960,13.147 L7.335,11.536 L8.027,10.851 L9.652,12.461 L13.316,8.829 Z\" />\n                    <path fill-rule=\"evenodd\" opacity=\"0.251\" fill=\"rgb(65, 54, 89)\"\n                          d=\"M17.334,11.334 L33.999,11.334 L33.999,12.167 L17.334,12.167 L17.334,11.334 Z\" />\n                </svg>",
        "svgTrusted": "",
        "css": "",
        "text": "Product Creation",
        "key": "productCreate",
        "tabs": "",
        "fields": "-hideFields,-contactRecipientEmailAddress,+formHeading,+formSecondaryHeading,+formIntroduction,+formButtonText,+formSubmissionMessage,-formSubscriberListID,-umbracoForm,-loginSuccessPage,-loginFormPage,-resetPasswordRequestPage,-resetPasswordPage,-resetPasswordEmail,+adminApprovalRequired,+emailConfirmationRequired,+memberConfirmationEmail,+setEmailAddressAsUsername"
      }
    ]
  }
}